{"c_deps": {}, "m_deps": {}, "full_fm": "package original;\n\nimport java.util.Collections;\nimport java.util.Comparator;\nimport java.util.List;\nclass OrderByPoints{\npublic static List<Object> orderByPoints(List<Object> nums) {\n        Collections.sort(nums, new Comparator<Object>() {\n            int digitsum(int n) {\n                boolean neg = false;\n                if (n < 0) {\n                    neg = true;\n                    n = -n;\n                }\n                int sum = 0;\n                while (n > 0) {\n                    if (n / 10 == 0 && neg)\n                        sum -= n % 10;\n                    else\n                        sum += n % 10;\n                    n = n / 10;\n                }\n                return sum;\n            }\n\n            public int compare(Object o1, Object o2) {\n                return digitsum((int) o1) - digitsum((int) o2);\n            }\n        });\n        return nums;\n    }\n}", "focal_method": "public static List<Object> orderByPoints(List<Object> nums)", "class_name": "OrderByPoints"}