[{"class_name": "FruitDistribution", "superclass": "", "interfaces": "", "c_sig": "class FruitDistribution", "has_constructor": false, "fields": [], "methods": [{"method_name": "fruitDistribution", "m_sig": "public static int fruitDistribution(String s, int n)", "class": "FruitDistribution", "source_code": "public static int fruitDistribution(String s, int n) {\n        int apples = 0;\n        int oranges = 0;\n        int mangoes = 0;\n        String[] words = s.split(\" \");\n        for (int i = 0; i < words.length; i++) {\n            if (words[i].equals(\"apples\")) {\n                apples = Integer.parseInt(words[i - 1]);\n            }\n            if (words[i].equals(\"oranges\")) {\n                oranges = Integer.parseInt(words[i - 1]);\n            }\n        }\n        mangoes = n - apples - oranges;\n        return mangoes;\n    }", "parameters": "fruitDistribution(String, int)", "modifiers": "public static", "return": "int", "signature": "int fruitDistribution(String s, int n)", "class_method_signature": "FruitDistribution.fruitDistribution(String s, int n)", "is_constructor": false, "use_field": true, "is_get_set": false, "m_deps": {"String": ["split()"]}}], "argument_list": "", "imports": [], "class_path": "../original/target/classes/original/id_67.java", "package": "package original;", "project_name": "original"}]